itsh_king_tiktok/__init__.py
itsh_king_tiktok/core.py
itsh_king_tiktok-0.1.0.dist-info/METADATA
itsh_king_tiktok-0.1.0.dist-info/WHEEL
itsh_king_tiktok-0.1.0.dist-info/top_level.txt
itsh_king_tiktok-0.1.0.dist-info/RECORD
