Metadata-Version: 2.4
Name: itsh_king_tiktok
Version: 0.1.0
Summary: Simple Python library
Requires-Python: >=3.7
Requires-Dist: requests
Dynamic: requires-dist
Dynamic: requires-python
Dynamic: summary
